iam_tools
