Metadata-Version: 2.1
Name: iam-tools
Version: 0.1.5
Summary: The IAM_tools - a Python package of tools to deal with IAM data.
Home-page: https://gitlab.com/dlab-indecol/iam_tools.git
Author: Radek Lonka, Konstantin Stadler
Author-email: radek.lonka@ntnu.no, konstantin.stadler@ntnu.no
License: BSD 3-Clause License
Project-URL: Issue Tracker, https://gitlab.com/dlab-indecol/iam_tools/-/issues
Project-URL: Documentation, https://iam-tools.readthedocs.io/en/latest/
Project-URL: Source Code, https://gitlab.com/dlab-indecol/iam_tools
Platform: UNKNOWN
Classifier: Programming Language :: Python :: 3.5
Classifier: Programming Language :: Python :: 3.6
Classifier: Programming Language :: Python :: 3 :: Only
Classifier: License :: OSI Approved :: BSD License
Classifier: Development Status :: 4 - Beta
Classifier: Environment :: Console
Classifier: Intended Audience :: End Users/Desktop
Classifier: Intended Audience :: Developers
Classifier: Intended Audience :: Science/Research
Classifier: Operating System :: MacOS :: MacOS X
Classifier: Operating System :: Microsoft :: Windows
Classifier: Operating System :: POSIX
Classifier: Programming Language :: Python
Classifier: Topic :: Scientific/Engineering
Classifier: Topic :: Utilities
